flake8_noreturn/__init__.py
flake8_noreturn/py.typed
flake8_noreturn-1.0.1.dist-info/LICENSE
flake8_noreturn-1.0.1.dist-info/WHEEL
flake8_noreturn-1.0.1.dist-info/METADATA
flake8_noreturn-1.0.1.dist-info/RECORD
