Metadata-Version: 2.1
Name: flake8-noreturn
Version: 1.0.1
Summary: A flake8 plugin to detect return None (-> None) type hints.
Home-page: https://github.com/izikeros/flake8-noreturn
License: MIT
Author: Krystian Safjan
Author-email: ksafjan@gmail.com
Requires-Python: >=3.8,<4.0
Classifier: License :: OSI Approved :: MIT License
Classifier: Programming Language :: Python :: 3
Classifier: Programming Language :: Python :: 3.8
Classifier: Programming Language :: Python :: 3.9
Classifier: Programming Language :: Python :: 3.10
Classifier: Programming Language :: Python :: 3.11
Requires-Dist: flake8 (>=5.0.4,<6.0.0)
Project-URL: Documentation, https://github.com/izikeros/flake8-noreturn
Project-URL: Repository, https://github.com/izikeros/flake8-noreturn
